{
  "current": {
    "temp": 7,
    "description": "небольшая облачность"
  },
  "hourly": [
    {
      "dt": 22,
      "temp": 7,
      "description": "небольшая облачность"
    },
    {
      "dt": 23,
      "temp": 7.96,
      "description": "переменная облачность"
    },
    {
      "dt": 0,
      "temp": 8.29,
      "description": "ясно"
    },
    {
      "dt": 1,
      "temp": 8.26,
      "description": "ясно"
    },
    {
      "dt": 2,
      "temp": 8.05,
      "description": "ясно"
    },
    {
      "dt": 3,
      "temp": 7.92,
      "description": "ясно"
    },
    {
      "dt": 4,
      "temp": 7.59,
      "description": "небольшая облачность"
    },
    {
      "dt": 5,
      "temp": 7.55,
      "description": "переменная облачность"
    },
    {
      "dt": 6,
      "temp": 7.44,
      "description": "облачно с прояснениями"
    },
    {
      "dt": 7,
      "temp": 7.12,
      "description": "облачно с прояснениями"
    },
    {
      "dt": 8,
      "temp": 8.06,
      "description": "пасмурно"
    },
    {
      "dt": 9,
      "temp": 9.7,
      "description": "пасмурно"
    },
    {
      "dt": 10,
      "temp": 11.48,
      "description": "пасмурно"
    },
    {
      "dt": 11,
      "temp": 12.84,
      "description": "пасмурно"
    },
    {
      "dt": 12,
      "temp": 13.8,
      "description": "пасмурно"
    },
    {
      "dt": 13,
      "temp": 14.49,
      "description": "пасмурно"
    },
    {
      "dt": 14,
      "temp": 14.91,
      "description": "пасмурно"
    },
    {
      "dt": 15,
      "temp": 15.25,
      "description": "пасмурно"
    },
    {
      "dt": 16,
      "temp": 15.15,
      "description": "пасмурно"
    },
    {
      "dt": 17,
      "temp": 14.49,
      "description": "пасмурно"
    },
    {
      "dt": 18,
      "temp": 12.16,
      "description": "пасмурно"
    },
    {
      "dt": 19,
      "temp": 10.41,
      "description": "облачно с прояснениями"
    },
    {
      "dt": 20,
      "temp": 9.77,
      "description": "облачно с прояснениями"
    },
    {
      "dt": 21,
      "temp": 9.36,
      "description": "облачно с прояснениями"
    },
    {
      "dt": 22,
      "temp": 9.03,
      "description": "облачно с прояснениями"
    },
    {
      "dt": 23,
      "temp": 8.71,
      "description": "облачно с прояснениями"
    },
    {
      "dt": 0,
      "temp": 8.45,
      "description": "ясно"
    },
    {
      "dt": 1,
      "temp": 8.19,
      "description": "ясно"
    },
    {
      "dt": 2,
      "temp": 7.92,
      "description": "ясно"
    },
    {
      "dt": 3,
      "temp": 7.71,
      "description": "ясно"
    },
    {
      "dt": 4,
      "temp": 7.5,
      "description": "ясно"
    },
    {
      "dt": 5,
      "temp": 7.3,
      "description": "ясно"
    },
    {
      "dt": 6,
      "temp": 7.03,
      "description": "переменная облачность"
    },
    {
      "dt": 7,
      "temp": 6.75,
      "description": "переменная облачность"
    },
    {
      "dt": 8,
      "temp": 7.34,
      "description": "переменная облачность"
    },
    {
      "dt": 9,
      "temp": 9.51,
      "description": "небольшая облачность"
    },
    {
      "dt": 10,
      "temp": 11.34,
      "description": "небольшая облачность"
    },
    {
      "dt": 11,
      "temp": 13,
      "description": "небольшая облачность"
    },
    {
      "dt": 12,
      "temp": 14.5,
      "description": "ясно"
    },
    {
      "dt": 13,
      "temp": 15.59,
      "description": "ясно"
    },
    {
      "dt": 14,
      "temp": 16.29,
      "description": "ясно"
    },
    {
      "dt": 15,
      "temp": 16.57,
      "description": "ясно"
    },
    {
      "dt": 16,
      "temp": 16.42,
      "description": "ясно"
    },
    {
      "dt": 17,
      "temp": 15.51,
      "description": "ясно"
    },
    {
      "dt": 18,
      "temp": 12.97,
      "description": "ясно"
    },
    {
      "dt": 19,
      "temp": 10.93,
      "description": "ясно"
    },
    {
      "dt": 20,
      "temp": 10.03,
      "description": "ясно"
    },
    {
      "dt": 21,
      "temp": 9.56,
      "description": "ясно"
    }
  ]
}
